tensorflow_projection_qm/__init__.py
tensorflow_projection_qm/py.typed
tensorflow_projection_qm/metrics/__init__.py
tensorflow_projection_qm/metrics/avg_local_error.py
tensorflow_projection_qm/metrics/continuity.py
tensorflow_projection_qm/metrics/distance_consistency.py
tensorflow_projection_qm/metrics/jaccard.py
tensorflow_projection_qm/metrics/mean_rel_rank_error.py
tensorflow_projection_qm/metrics/metric.py
tensorflow_projection_qm/metrics/neighborhood_hit.py
tensorflow_projection_qm/metrics/neighbors.py
tensorflow_projection_qm/metrics/pearson_correlation.py
tensorflow_projection_qm/metrics/procrustes.py
tensorflow_projection_qm/metrics/shepard_goodness.py
tensorflow_projection_qm/metrics/stress.py
tensorflow_projection_qm/metrics/trustworthiness.py
tensorflow_projection_qm/util/__init__.py
tensorflow_projection_qm/util/distance.py
tensorflow_projection_qm-0.2.3.dist-info/METADATA
tensorflow_projection_qm-0.2.3.dist-info/WHEEL
tensorflow_projection_qm-0.2.3.dist-info/licenses/LICENSE
tensorflow_projection_qm-0.2.3.dist-info/RECORD
