Metadata-Version: 2.3
Name: tensorflow-projection-qm
Version: 0.2.3
Summary: A package with fast, TensorFlow-based implementations of projection (i.e., dimensionality reduction) quality metrics.
Project-URL: Repository, https://github.com/amreis/tf-projection-qm
Project-URL: Homepage, https://github.com/amreis/tf-projection-qm
Author-email: Alister Machado <alister.reis@gmail.com>
License: MIT License
License-File: LICENSE
Keywords: data visualization,dimensionality reduction,projection,quality metrics,visualization
Classifier: Development Status :: 3 - Alpha
Classifier: License :: OSI Approved :: MIT License
Classifier: Programming Language :: Python :: 3
Classifier: Programming Language :: Python :: 3.9
Classifier: Programming Language :: Python :: 3.10
Classifier: Programming Language :: Python :: 3.11
Classifier: Programming Language :: Python :: 3.12
Classifier: Topic :: Scientific/Engineering :: Visualization
Requires-Python: >=3.9
Requires-Dist: numpy<2,>=1.24
Requires-Dist: scipy>=1.13.1
Requires-Dist: tensorflow>=2.15; python_version < '3.12'
Requires-Dist: tensorflow>=2.17; python_version >= '3.12'
Provides-Extra: and-cuda
Requires-Dist: tensorflow[and-cuda]>=2.15; (python_version < '3.12') and extra == 'and-cuda'
Requires-Dist: tensorflow[and-cuda]>=2.17; (python_version >= '3.12') and extra == 'and-cuda'
